letterboxd_rss/__init__.py
letterboxd_rss/base.py
letterboxd_rss/cli.py
letterboxd_rss/constants.py
letterboxd_rss/feed.py
letterboxd_rss/parsing.py
letterboxd_rss/session.py
letterboxd_rss/utils.py
letterboxd_rss-0.4.0.dist-info/LICENSE
letterboxd_rss-0.4.0.dist-info/METADATA
letterboxd_rss-0.4.0.dist-info/WHEEL
letterboxd_rss-0.4.0.dist-info/entry_points.txt
letterboxd_rss-0.4.0.dist-info/RECORD
