Metadata-Version: 2.1
Name: letterboxd-rss
Version: 0.4.0
Summary: Generate an RSS feed from your letterboxd.com watchlist
Home-page: https://github.com/janw/letterboxd-rss
License: Apache-2.0
Author: Jan Willhaus
Author-email: mail@janwillhaus.de
Requires-Python: >=3.9,<4.0
Classifier: Development Status :: 3 - Alpha
Classifier: License :: OSI Approved :: Apache Software License
Classifier: Programming Language :: Python :: 3
Classifier: Programming Language :: Python :: 3.9
Classifier: Programming Language :: Python :: 3.10
Classifier: Programming Language :: Python :: 3.11
Classifier: Programming Language :: Python :: 3.12
Classifier: Programming Language :: Python :: 3.13
Classifier: Topic :: Internet
Classifier: Topic :: Internet :: WWW/HTTP :: Dynamic Content
Classifier: Topic :: Internet :: WWW/HTTP :: Dynamic Content :: News/Diary
Requires-Dist: beautifulsoup4 (>=4,<5)
Requires-Dist: feedgen (>=1.0,<2.0)
Requires-Dist: requests (>=2,<3)
Project-URL: Repository, https://github.com/janw/letterboxd-rss
